berater/__init__.py
berater-0.0.1.dist-info/LICENSE.txt
berater-0.0.1.dist-info/METADATA
berater-0.0.1.dist-info/WHEEL
berater-0.0.1.dist-info/top_level.txt
berater-0.0.1.dist-info/RECORD
