Metadata-Version: 2.1
Name: berater
Version: 0.0.1
Summary: do work...within limits
Home-page: https://github.com/dpep/berater_py
Author: Daniel Pepper
License: MIT
Platform: any
Classifier: License :: OSI Approved :: MIT License
Classifier: Natural Language :: English
Classifier: Operating System :: OS Independent
Classifier: Topic :: Utilities
